LICENSE.txt
MANIFEST.in
README.md
setup.cfg
setup.py
creme/__init__.py
creme/manage.py
creme/settings.py
creme/urls.py
creme/activities/__init__.py
creme/activities/actions.py
creme/activities/apps.py
creme/activities/bricks.py
creme/activities/buttons.py
creme/activities/cloners.py
creme/activities/constants.py
creme/activities/crudity_register.py
creme/activities/custom_forms.py
creme/activities/enumerators.py
creme/activities/menu.py
creme/activities/populate.py
creme/activities/setting_keys.py
creme/activities/signals.py
creme/activities/statistics.py
creme/activities/urls.py
creme/activities/utils.py
creme/activities/forms/__init__.py
creme/activities/forms/activity.py
creme/activities/forms/activity_type.py
creme/activities/forms/bricks.py
creme/activities/forms/bulk_update.py
creme/activities/forms/buttons.py
creme/activities/forms/calendar.py
creme/activities/forms/config.py
creme/activities/forms/fields.py
creme/activities/forms/mass_import.py
creme/activities/locale/fr/LC_MESSAGES/django.mo
creme/activities/locale/fr/LC_MESSAGES/django.po
creme/activities/locale/fr/LC_MESSAGES/djangojs.mo
creme/activities/locale/fr/LC_MESSAGES/djangojs.po
creme/activities/management/__init__.py
creme/activities/management/commands/__init__.py
creme/activities/management/commands/activities_create_default_calendars.py
creme/activities/migrations/0001_initial.py
creme/activities/migrations/0029_v2_7__floating_type_choices.py
creme/activities/migrations/0030_v2_7__calendarconfigitem_view_day.py
creme/activities/migrations/__init__.py
creme/activities/models/__init__.py
creme/activities/models/activity.py
creme/activities/models/calendar.py
creme/activities/models/config.py
creme/activities/models/other_models.py
creme/activities/static/activities/js/activities-calendar.js
creme/activities/static/activities/js/activities.js
creme/activities/static/activities/js/bricks.js
creme/activities/static/activities/js/calendar.js
creme_crm.egg-info/PKG-INFO
creme_crm.egg-info/SOURCES.txt
creme_crm.egg-info/dependency_links.txt
creme_crm.egg-info/entry_points.txt
creme_crm.egg-info/not-zip-safe
creme_crm.egg-info/requires.txt
creme_crm.egg-info/top_level.txt
