Metadata-Version: 2.4
Name: creme-crm
Version: 2.7.3
Summary: A CRM software using the django web framework
Home-page: https://www.cremecrm.com
Author: hybird.org
Author-email: contact@hybird.org
License: AGPL-3.0
Project-URL: Release notes, https://raw.githubusercontent.com/HybirdCorp/creme_crm/main/CHANGELOG.txt
Project-URL: Source, https://github.com/HybirdCorp/creme_crm
Project-URL: Tracker, https://github.com/HybirdCorp/creme_crm/issues
Keywords: CRM
Classifier: Development Status :: 5 - Production/Stable
Classifier: Environment :: Web Environment
Classifier: Framework :: Django
Classifier: Intended Audience :: Customer Service
Classifier: Intended Audience :: Developers
Classifier: Intended Audience :: End Users/Desktop
Classifier: License :: OSI Approved :: GNU Affero General Public License v3
Classifier: Natural Language :: English
Classifier: Natural Language :: French
Classifier: Operating System :: OS Independent
Classifier: Programming Language :: Python :: 3 :: Only
Classifier: Programming Language :: Python :: 3.10
Classifier: Programming Language :: Python :: 3.11
Classifier: Programming Language :: Python :: 3.12
Classifier: Programming Language :: Python :: 3.13
Classifier: Topic :: Office/Business
Requires-Python: >=3.10
License-File: LICENSE.txt
Requires-Dist: django~=5.2.9
Requires-Dist: redis~=6.2.0
Requires-Dist: Pillow~=11.3.0
Requires-Dist: python-dateutil~=2.8.2
Requires-Dist: bleach[css]~=6.2.0
Requires-Dist: django-formtools~=2.5.1
Requires-Dist: cryptography~=45.0.7
Requires-Dist: xlrd~=2.0.2
Requires-Dist: xlwt~=1.3.0
Requires-Dist: openpyxl~=3.1.5
Requires-Dist: csscompressor~=0.9.5
Requires-Dist: rjsmin~=1.2.2
Requires-Dist: xhtml2pdf==0.2.17
Requires-Dist: pywin32; platform_system == "Windows"
Provides-Extra: dev
Requires-Dist: coverage~=7.9.1; extra == "dev"
Requires-Dist: flake8~=7.2.0; extra == "dev"
Requires-Dist: isort~=6.0.1; extra == "dev"
Requires-Dist: ipython; extra == "dev"
Requires-Dist: parameterized~=0.9.0; extra == "dev"
Requires-Dist: tblib~=3.0.0; extra == "dev"
Requires-Dist: django-extensions~=4.1; extra == "dev"
Requires-Dist: polib~=1.2.0; extra == "dev"
Requires-Dist: pyenchant~=3.2.2; extra == "dev"
Requires-Dist: beautifulsoup4~=4.12.3; extra == "dev"
Provides-Extra: mysql
Requires-Dist: mysqlclient~=2.2.4; extra == "mysql"
Provides-Extra: pgsql
Requires-Dist: psycopg~=3.1.18; extra == "pgsql"
Provides-Extra: billing-weasyprint
Requires-Dist: weasyprint~=66.0; extra == "billing-weasyprint"
Dynamic: license-file
